{"namedChunkGroups":{"polyfill":{"name":"polyfill","assets":[{"name":"webpack-runtime-fba9ff81695553e9a256.js","size":3845},{"name":"polyfill-9fb46b10d19de12b5421.js","size":82571}],"filteredAssets":0,"assetsSize":86416,"filteredAuxiliaryAssets":2,"auxiliaryAssetsSize":217216},"app":{"name":"app","assets":[{"name":"webpack-runtime-fba9ff81695553e9a256.js","size":3845},{"name":"framework-8e47f3d8b0a5c9954a53.js","size":128945},{"name":"styles.ebd1b859a97d52d13269.css","size":10505},{"name":"app-1abdfe8739c03cc72289.js","size":72910}],"filteredAssets":0,"assetsSize":216205,"filteredAuxiliaryAssets":3,"auxiliaryAssetsSize":670477},"component---src-pages-404-js":{"name":"component---src-pages-404-js","assets":[{"name":"commons-a97a1e0fd41373634a1e.js","size":18627},{"name":"component---src-pages-404-js-0e67fe10c6be3cbeadb9.js","size":567}],"filteredAssets":0,"assetsSize":19194,"filteredAuxiliaryAssets":2,"auxiliaryAssetsSize":73537},"component---src-pages-automation-js":{"name":"component---src-pages-automation-js","assets":[{"name":"commons-a97a1e0fd41373634a1e.js","size":18627},{"name":"component---src-pages-automation-js-944eff898443d508735d.js","size":5796}],"filteredAssets":0,"assetsSize":24423,"filteredAuxiliaryAssets":2,"auxiliaryAssetsSize":85757},"component---src-pages-index-js":{"name":"component---src-pages-index-js","assets":[{"name":"commons-a97a1e0fd41373634a1e.js","size":18627},{"name":"component---src-pages-index-js-6fb33e81b45dda924552.js","size":2448}],"filteredAssets":0,"assetsSize":21075,"filteredAuxiliaryAssets":2,"auxiliaryAssetsSize":77439},"component---src-pages-react-js":{"name":"component---src-pages-react-js","assets":[{"name":"commons-a97a1e0fd41373634a1e.js","size":18627},{"name":"component---src-pages-react-js-bd0c69f10bf12bf4db86.js","size":6662}],"filteredAssets":0,"assetsSize":25289,"filteredAuxiliaryAssets":2,"auxiliaryAssetsSize":88738}},"assetsByChunkName":{"polyfill":["webpack-runtime-fba9ff81695553e9a256.js","polyfill-9fb46b10d19de12b5421.js"],"app":["webpack-runtime-fba9ff81695553e9a256.js","framework-8e47f3d8b0a5c9954a53.js","styles.ebd1b859a97d52d13269.css","app-1abdfe8739c03cc72289.js"],"component---src-pages-404-js":["commons-a97a1e0fd41373634a1e.js","component---src-pages-404-js-0e67fe10c6be3cbeadb9.js"],"component---src-pages-automation-js":["commons-a97a1e0fd41373634a1e.js","component---src-pages-automation-js-944eff898443d508735d.js"],"component---src-pages-index-js":["commons-a97a1e0fd41373634a1e.js","component---src-pages-index-js-6fb33e81b45dda924552.js"],"component---src-pages-react-js":["commons-a97a1e0fd41373634a1e.js","component---src-pages-react-js-bd0c69f10bf12bf4db86.js"]},"childAssetsByChunkName":{}}